.editorconfig
.travis.yml
AUTHORS.rst
CHANGELOG.rst
CONTRIBUTING.rst
LICENSE
MANIFEST.in
README.rst
setup.cfg
setup.py
tox.ini
docs/Makefile
docs/authors.rst
docs/changelog.rst
docs/conf.py
docs/contributing.rst
docs/index.rst
docs/license.rst
docs/make.bat
docs/readme.rst
docs/requirements.txt
requirements/base.txt
requirements/tests.txt
tests/__init__.py
tests/test_nothing.py
voxplex/__init__.py
voxplex/cli.py
voxplex/config.py
voxplex/local.py
voxplex/remote.py
voxplex/sync.py
voxplex.egg-info/PKG-INFO
voxplex.egg-info/SOURCES.txt
voxplex.egg-info/dependency_links.txt
voxplex.egg-info/entry_points.txt
voxplex.egg-info/not-zip-safe
voxplex.egg-info/requires.txt
voxplex.egg-info/top_level.txt